Metadata-Version: 2.1
Name: repos
Version: 0.2.0
Summary: Manages git repos inside a directory
Author: jpedro
Author-email: jpedro.barbosa@gmail.com
License: MIT
Keywords: git repos
Classifier: Development Status :: 3 - Alpha
Classifier: Intended Audience :: Developers
Classifier: Topic :: Software Development :: Build Tools
Classifier: License :: OSI Approved :: MIT License
